clovers_groupmate_waifu/__init__.py
clovers_groupmate_waifu/clovers.py
clovers_groupmate_waifu/config.py
clovers_groupmate_waifu/data.py
clovers_groupmate_waifu/utils.py
clovers_groupmate_waifu-0.2.7.dist-info/LICENSE
clovers_groupmate_waifu-0.2.7.dist-info/METADATA
clovers_groupmate_waifu-0.2.7.dist-info/WHEEL
clovers_groupmate_waifu-0.2.7.dist-info/RECORD
