Metadata-Version: 2.3
Name: clovers-groupmate-waifu
Version: 0.2.7
Summary: 
Author: KarisAya
Author-email: karisaya@foxmail.com
Requires-Python: >=3.12,<4.0.0
Classifier: Programming Language :: Python :: 3
Classifier: Programming Language :: Python :: 3.12
Classifier: Programming Language :: Python :: 3.13
Requires-Dist: clovers (>=0.4.8,<0.5.0)
Requires-Dist: clovers-apscheduler (>=0.2.2,<0.3.0)
Requires-Dist: httpx (>=0.28.1,<0.29.0)
Requires-Dist: linecard (>=0.2.0,<0.3.0)
Requires-Dist: pydantic (>=2.10.6,<3.0.0)
